README.md
setup.py
acwrite.egg-info/PKG-INFO
acwrite.egg-info/SOURCES.txt
acwrite.egg-info/dependency_links.txt
acwrite.egg-info/requires.txt
acwrite.egg-info/top_level.txt
acwriting/__init__.py
acwriting/PyDictionary/__init__.py
acwriting/PyDictionary/core.py
acwriting/PyDictionary/script.py
acwriting/PyDictionary/test_pydictionary.py
acwriting/PyDictionary/utils.py
acwriting/googletrans/__init__.py
acwriting/googletrans/client.py
acwriting/googletrans/constants.py
acwriting/googletrans/gtoken.py
acwriting/googletrans/models.py
acwriting/googletrans/urls.py
acwriting/googletrans/utils.py
acwriting/latexify/__init__.py
acwriting/latexify/core.py
bin/acword
test/test_utils.py