Metadata-Version: 2.1
Name: acwrite
Version: 1.1
Summary: A python package for writing academic papers
Home-page: https://github.com/Yoki0/acwriting
Author: Yi Yu
Author-email: q1499114179@gmail.com
License: UNKNOWN
Platform: UNKNOWN
Classifier: Programming Language :: Python :: 3
Classifier: License :: OSI Approved :: MIT License
Classifier: Operating System :: OS Independent
Requires-Python: >=3.6
